tinytina/__init__.py
tinytina/main.py
tinytina-0.1.0.dist-info/entry_points.txt
tinytina-0.1.0.dist-info/METADATA
tinytina-0.1.0.dist-info/WHEEL
tinytina-0.1.0.dist-info/RECORD
