Metadata-Version: 2.1
Name: tinytina
Version: 0.1.0
Summary: 
Author: arthur-trt
Author-email: atrouill@student.42.fr
Requires-Python: >=3.10,<4.0
Classifier: Programming Language :: Python :: 3
Classifier: Programming Language :: Python :: 3.10
Classifier: Programming Language :: Python :: 3.11
Requires-Dist: beaupy (>=3.2.0,<4.0.0)
Requires-Dist: ttwl-cli-saveedit (>=1.0.0,<2.0.0)
Requires-Dist: userpaths (>=0.1.3,<0.2.0)
